Workbook
Name IQ_CH: 110000
Name IQ_CQ: 5000
Name IQ_CY: 10000
Name IQ_DAILY: 500000
Name IQ_FH: 100000
Name IQ_FQ: 500
Name IQ_FY: 1000
Name IQ_LTM: 2000
Name IQ_MONTH: 15000
Name IQ_NTM: 6000
Name IQ_WEEK: 50000
Name IQ_YTD: 3000

Sheet Executive Dashboard
A1: UK E-Commerce Sales Forecast - Executive Dashboard
A3: Next 12M Projected Revenue | B3: =SUM(B11:B22) -> 9216894.8
A4: Model Baseline MAPE% | B4: ='Model Validation'!I1 -> 0.21952051
A5: Q4 Peak Working Capital Needed | B5: =(MAX(B11:B22)-AVERAGE(B11:B22))*B24 -> 323831.94
A7: Scenario: | B7: Base Case
B8: {=_xlfn.SWITCH($B$7,"Base Case",1,"Optimistic (+10%)",1.1,"Stress Case (-10%)",0.9,1)} -> 1
A10: Date | B10: Scenario Forecast
A11: ='Forecasting Engine'!B26 -> 40878 | B11: ='Forecasting Engine'!D26*$B$8 -> 1122333.5
A12: ='Forecasting Engine'!B27 -> 40909 | B12: ='Forecasting Engine'!D27*$B$8 -> 587605.14
A13: ='Forecasting Engine'!B28 -> 40940 | B13: ='Forecasting Engine'!D28*$B$8 -> 461944.27
A14: ='Forecasting Engine'!B29 -> 40969 | B14: ='Forecasting Engine'!D29*$B$8 -> 618656.08
A15: ='Forecasting Engine'!B30 -> 41000 | B15: ='Forecasting Engine'!D30*$B$8 -> 514638.16
A16: ='Forecasting Engine'!B31 -> 41030 | B16: ='Forecasting Engine'!D31*$B$8 -> 655937.86
A17: ='Forecasting Engine'!B32 -> 41061 | B17: ='Forecasting Engine'!D32*$B$8 -> 684052.85
A18: ='Forecasting Engine'!B33 -> 41091 | B18: ='Forecasting Engine'!D33*$B$8 -> 647813.39
A19: ='Forecasting Engine'!B34 -> 41122 | B19: ='Forecasting Engine'!D34*$B$8 -> 665089.98
A20: ='Forecasting Engine'!B35 -> 41153 | B20: ='Forecasting Engine'!D35*$B$8 -> 886769.94
A21: ='Forecasting Engine'!B36 -> 41183 | B21: ='Forecasting Engine'!D36*$B$8 -> 1015193.7
A22: ='Forecasting Engine'!B37 -> 41214 | B22: ='Forecasting Engine'!D37*$B$8 -> 1356859.9
A24: Assumption: COGS % of Revenue (editable) | B24: 0.55

Sheet Forecasting Engine
A1: year_month | B1: Date | C1: Historical Revenue | D1: Forecast | E1: Lower 95% CI | F1: Upper 95% CI | H1: Model Parameters
A2: 2009-12 | B2: 40148 | C2: 729781.68 | H2: Alpha (level) | I2: =_xlfn.FORECAST.ETS.STAT($C$2:$C$25,$B$2:$B$25,1,12,1,1) -> 0.998
A3: 2010-01 | B3: 40179 | C3: 484647.53 | H3: Beta (trend) | I3: =_xlfn.FORECAST.ETS.STAT($C$2:$C$25,$B$2:$B$25,2,12,1,1) -> 0.099
A4: 2010-02 | B4: 40210 | C4: 447842.01 | H4: Gamma (seasonal) | I4: =_xlfn.FORECAST.ETS.STAT($C$2:$C$25,$B$2:$B$25,3,12,1,1) -> 0.001
A5: 2010-03 | B5: 40238 | C5: 670956.71
A6: 2010-04 | B6: 40269 | C6: 558114.09 | H6: Detected seasonality length | I6: =_xlfn.FORECAST.ETS.SEASONALITY($C$2:$C$25,$B$2:$B$25,1,1) -> 0
A7: 2010-05 | B7: 40299 | C7: 553099.74
A8: 2010-06 | B8: 40330 | C8: 603400.7
A9: 2010-07 | B9: 40360 | C9: 552195.31
A10: 2010-08 | B10: 40391 | C10: 582147.37
A11: 2010-09 | B11: 40422 | C11: 727454.58
A12: 2010-10 | B12: 40452 | C12: 947424.5
A13: 2010-11 | B13: 40483 | C13: 1251705.1
A14: 2010-12 | B14: 40513 | C14: 1084990
A15: 2011-01 | B15: 40544 | C15: 547167.61
A16: 2011-02 | B16: 40575 | C16: 418933.95
A17: 2011-03 | B17: 40603 | C17: 572873.13
A18: 2011-04 | B18: 40634 | C18: 466132.15
... A25: 2011-11 | B25: 40848 | C25: 1286274.8
A26: =TEXT(B26, "yyyy-mm") -> 2011-12 | B26: 40878 | D26: =_xlfn.FORECAST.ETS(B26,$C$2:$C$25,$B$2:$B$25,12,1,1) -> 1122333.5 | E26: =D26-_xlfn.FORECAST.ETS.CONFINT($B26,$C$2:$C$25,$B$2:$B$25,0.95,12,1,1) -> 960935.03 | F26: =D26+_xlfn.FORECAST.ETS.CONFINT($B26,$C$2:$C$25,$B$2:$B$25,0.95,12,1,1) -> 1283732
A27: =TEXT(B27, "yyyy-mm") -> 2012-01 | B27: =EDATE(B26,1) -> 40909 | D27: =_xlfn.FORECAST.ETS(B27,$C$2:$C$25,$B$2:$B$25,12,1,1) -> 587605.14 | E27: =D27-_xlfn.FORECAST.ETS.CONFINT($B27,$C$2:$C$25,$B$2:$B$25,0.95,12,1,1) -> 348027.08 | F27: =D27+_xlfn.FORECAST.ETS.CONFINT($B27,$C$2:$C$25,$B$2:$B$25,0.95,12,1,1) -> 827183.2
A28: =TEXT(B28, "yyyy-mm") -> 2012-02 | B28: =EDATE(B27,1) -> 40940 | D28: =_xlfn.FORECAST.ETS(B28,$C$2:$C$25,$B$2:$B$25,12,1,1) -> 461944.27 | E28: =D28-_xlfn.FORECAST.ETS.CONFINT($B28,$C$2:$C$25,$B$2:$B$25,0.95,12,1,1) -> 154276.87 | F28: =D28+_xlfn.FORECAST.ETS.CONFINT($B28,$C$2:$C$25,$B$2:$B$25,0.95,12,1,1) -> 769611.68
A29: =TEXT(B29, "yyyy-mm") -> 2012-03 | B29: =EDATE(B28,1) -> 40969 | D29: =_xlfn.FORECAST.ETS(B29,$C$2:$C$25,$B$2:$B$25,12,1,1) -> 618656.08 | E29: =D29-_xlfn.FORECAST.ETS.CONFINT($B29,$C$2:$C$25,$B$2:$B$25,0.95,12,1,1) -> 246708.7 | F29: =D29+_xlfn.FORECAST.ETS.CONFINT($B29,$C$2:$C$25,$B$2:$B$25,0.95,12,1,1) -> 990603.46
A30: =TEXT(B30, "yyyy-mm") -> 2012-04 | B30: =EDATE(B29,1) -> 41000 | D30: =_xlfn.FORECAST.ETS(B30,$C$2:$C$25,$B$2:$B$25,12,1,1) -> 514638.16 | E30: =D30-_xlfn.FORECAST.ETS.CONFINT($B30,$C$2:$C$25,$B$2:$B$25,0.95,12,1,1) -> 79936.963 | F30: =D30+_xlfn.FORECAST.ETS.CONFINT($B30,$C$2:$C$25,$B$2:$B$25,0.95,12,1,1) -> 949339.36
A31: =TEXT(B31, "yyyy-mm") -> 2012-05 | B31: =EDATE(B30,1) -> 41030 | D31: =_xlfn.FORECAST.ETS(B31,$C$2:$C$25,$B$2:$B$25,12,1,1) -> 655937.86 | E31: =D31-_xlfn.FORECAST.ETS.CONFINT($B31,$C$2:$C$25,$B$2:$B$25,0.95,12,1,1) -> 158916.04 | F31: =D31+_xlfn.FORECAST.ETS.CONFINT($B31,$C$2:$C$25,$B$2:$B$25,0.95,12,1,1) -> 1152959.7
A32: =TEXT(B32, "yyyy-mm") -> 2012-06 | B32: =EDATE(B31,1) -> 41061 | D32: =_xlfn.FORECAST.ETS(B32,$C$2:$C$25,$B$2:$B$25,12,1,1) -> 684052.85 | E32: =D32-_xlfn.FORECAST.ETS.CONFINT($B32,$C$2:$C$25,$B$2:$B$25,0.95,12,1,1) -> 124542.22 | F32: =D32+_xlfn.FORECAST.ETS.CONFINT($B32,$C$2:$C$25,$B$2:$B$25,0.95,12,1,1) -> 1243563.5
A33: =TEXT(B33, "yyyy-mm") -> 2012-07 | B33: =EDATE(B32,1) -> 41091 | D33: =_xlfn.FORECAST.ETS(B33,$C$2:$C$25,$B$2:$B$25,12,1,1) -> 647813.39 | E33: =D33-_xlfn.FORECAST.ETS.CONFINT($B33,$C$2:$C$25,$B$2:$B$25,0.95,12,1,1) -> 25286.186 | F33: =D33+_xlfn.FORECAST.ETS.CONFINT($B33,$C$2:$C$25,$B$2:$B$25,0.95,12,1,1) -> 1270340.6
A34: =TEXT(B34, "yyyy-mm") -> 2012-08 | B34: =EDATE(B33,1) -> 41122 | D34: =_xlfn.FORECAST.ETS(B34,$C$2:$C$25,$B$2:$B$25,12,1,1) -> 665089.98 | E34: =D34-_xlfn.FORECAST.ETS.CONFINT($B34,$C$2:$C$25,$B$2:$B$25,0.95,12,1,1) -> -21208.241 | F34: =D34+_xlfn.FORECAST.ETS.CONFINT($B34,$C$2:$C$25,$B$2:$B$25,0.95,12,1,1) -> 1351388.2
A35: =TEXT(B35, "yyyy-mm") -> 2012-09 | B35: =EDATE(B34,1) -> 41153 | D35: =_xlfn.FORECAST.ETS(B35,$C$2:$C$25,$B$2:$B$25,12,1,1) -> 886769.94 | E35: =D35-_xlfn.FORECAST.ETS.CONFINT($B35,$C$2:$C$25,$B$2:$B$25,0.95,12,1,1) -> 135798.48 | F35: =D35+_xlfn.FORECAST.ETS.CONFINT($B35,$C$2:$C$25,$B$2:$B$25,0.95,12,1,1) -> 1637741.4
A36: =TEXT(B36, "yyyy-mm") -> 2012-10 | B36: =EDATE(B35,1) -> 41183 | D36: =_xlfn.FORECAST.ETS(B36,$C$2:$C$25,$B$2:$B$25,12,1,1) -> 1015193.7 | E36: =D36-_xlfn.FORECAST.ETS.CONFINT($B36,$C$2:$C$25,$B$2:$B$25,0.95,12,1,1) -> 198548.5 | F36: =D36+_xlfn.FORECAST.ETS.CONFINT($B36,$C$2:$C$25,$B$2:$B$25,0.95,12,1,1) -> 1831838.9
A37: =TEXT(B37, "yyyy-mm") -> 2012-11 | B37: =EDATE(B36,1) -> 41214 | D37: =_xlfn.FORECAST.ETS(B37,$C$2:$C$25,$B$2:$B$25,12,1,1) -> 1356859.9 | E37: =D37-_xlfn.FORECAST.ETS.CONFINT($B37,$C$2:$C$25,$B$2:$B$25,0.95,12,1,1) -> 473474.56 | F37: =D37+_xlfn.FORECAST.ETS.CONFINT($B37,$C$2:$C$25,$B$2:$B$25,0.95,12,1,1) -> 2240245.3

Sheet Model Validation
A1: year_month | B1: Date | C1: Actual Revenue | D1: Sample | E1: Backtest Forecast | F1: APE | H1: MAPE (6-month holdout) | I1: =AVERAGE(F20:F25) -> 0.21952051
A2: 2009-12 | B2: 40148 | C2: 729781.68 | D2: Train | H2: Detected seasonality (training only, 18mo) | I2: =_xlfn.FORECAST.ETS.SEASONALITY($C$2:$C$19,$B$2:$B$19,1,1) -> 0
A3: 2010-01 | B3: 40179 | C3: 484647.53 | D3: Train
A4: 2010-02 | B4: 40210 | C4: 447842.01 | D4: Train | H4: Interpretation | I4: 22% MAPE reflects the limits of an 18-month training window (only 1.5 seasonal cycles); Excel's auto-detection found no reliable cycle, not the true 12-month retail calendar. The production forecast in Tab 2 uses the full 24 months, where seasonality is forced explicitly rather than auto-detected, so it isn't subject to the same detection limitation.
A5: 2010-03 | B5: 40238 | C5: 670956.71 | D5: Train
A6: 2010-04 | B6: 40269 | C6: 558114.09 | D6: Train
A7: 2010-05 | B7: 40299 | C7: 553099.74 | D7: Train
A8: 2010-06 | B8: 40330 | C8: 603400.7 | D8: Train
A9: 2010-07 | B9: 40360 | C9: 552195.31 | D9: Train
A10: 2010-08 | B10: 40391 | C10: 582147.37 | D10: Train
A11: 2010-09 | B11: 40422 | C11: 727454.58 | D11: Train
A12: 2010-10 | B12: 40452 | C12: 947424.5 | D12: Train
A13: 2010-11 | B13: 40483 | C13: 1251705.1 | D13: Train
A14: 2010-12 | B14: 40513 | C14: 1084990 | D14: Train
A15: 2011-01 | B15: 40544 | C15: 547167.61 | D15: Train
A16: 2011-02 | B16: 40575 | C16: 418933.95 | D16: Train
... A19: 2011-05 | B19: 40664 | C19: 619391.15 | D19: Train
A20: 2011-06 | B20: 40695 | C20: 606195.96 | D20: Test | E20: =_xlfn.FORECAST.ETS(B20,$C$2:$C$19,$B$2:$B$19,1,1,1) -> 642640.05 | F20: =ABS(C20-E20)/C20 -> 0.060119328
A21: 2011-07 | B21: 40725 | C21: 578224.68 | D21: Test | E21: =_xlfn.FORECAST.ETS(B21,$C$2:$C$19,$B$2:$B$19,1,1,1) -> 647004.68 | F21: =ABS(C21-E21)/C21 -> 0.1189503
A22: 2011-08 | B22: 40756 | C22: 579958.6 | D22: Test | E22: =_xlfn.FORECAST.ETS(B22,$C$2:$C$19,$B$2:$B$19,1,1,1) -> 651369.31 | F22: =ABS(C22-E22)/C22 -> 0.1231307
A23: 2011-09 | B23: 40787 | C23: 878029.11 | D23: Test | E23: =_xlfn.FORECAST.ETS(B23,$C$2:$C$19,$B$2:$B$19,1,1,1) -> 655733.94 | F23: =ABS(C23-E23)/C23 -> 0.25317517
A24: 2011-10 | B24: 40817 | C24: 914678.25 | D24: Test | E24: =_xlfn.FORECAST.ETS(B24,$C$2:$C$19,$B$2:$B$19,1,1,1) -> 660098.56 | F24: =ABS(C24-E24)/C24 -> 0.27832704
A25: 2011-11 | B25: 40848 | C25: 1286274.8 | D25: Test | E25: =_xlfn.FORECAST.ETS(B25,$C$2:$C$19,$B$2:$B$19,1,1,1) -> 664463.19 | F25: =ABS(C25-E25)/C25 -> 0.48342049
